MANIFEST.in
README.rst
setup.py
docs/cfg.txt
docs/compiler.md
docs/fairyscript.md
fairyscript/__init__.py
fairyscript/pretty.py
fairyscript.egg-info/PKG-INFO
fairyscript.egg-info/SOURCES.txt
fairyscript.egg-info/dependency_links.txt
fairyscript.egg-info/entry_points.txt
fairyscript.egg-info/requires.txt
fairyscript.egg-info/top_level.txt
fairyscript/compile/__init__.py
fairyscript/compile/analyze.py
fairyscript/compile/fey.py
fairyscript/compile/renpy.py
fairyscript/compile/word.py
fairyscript/docx/__init__.py
fairyscript/docx/api.py
fairyscript/docx/blkcntnr.py
fairyscript/docx/compat.py
fairyscript/docx/document.py
fairyscript/docx/exceptions.py
fairyscript/docx/package.py
fairyscript/docx/section.py
fairyscript/docx/shape.py
fairyscript/docx/shared.py
fairyscript/docx/table.py
fairyscript/docx/dml/__init__.py
fairyscript/docx/dml/color.py
fairyscript/docx/enum/__init__.py
fairyscript/docx/enum/base.py
fairyscript/docx/enum/dml.py
fairyscript/docx/enum/section.py
fairyscript/docx/enum/shape.py
fairyscript/docx/enum/style.py
fairyscript/docx/enum/table.py
fairyscript/docx/enum/text.py
fairyscript/docx/image/__init__.py
fairyscript/docx/image/bmp.py
fairyscript/docx/image/constants.py
fairyscript/docx/image/exceptions.py
fairyscript/docx/image/gif.py
fairyscript/docx/image/helpers.py
fairyscript/docx/image/image.py
fairyscript/docx/image/jpeg.py
fairyscript/docx/image/png.py
fairyscript/docx/image/tiff.py
fairyscript/docx/opc/__init__.py
fairyscript/docx/opc/compat.py
fairyscript/docx/opc/constants.py
fairyscript/docx/opc/coreprops.py
fairyscript/docx/opc/exceptions.py
fairyscript/docx/opc/oxml.py
fairyscript/docx/opc/package.py
fairyscript/docx/opc/packuri.py
fairyscript/docx/opc/part.py
fairyscript/docx/opc/phys_pkg.py
fairyscript/docx/opc/pkgreader.py
fairyscript/docx/opc/pkgwriter.py
fairyscript/docx/opc/rel.py
fairyscript/docx/opc/shared.py
fairyscript/docx/opc/spec.py
fairyscript/docx/opc/parts/__init__.py
fairyscript/docx/opc/parts/coreprops.py
fairyscript/docx/oxml/__init__.py
fairyscript/docx/oxml/coreprops.py
fairyscript/docx/oxml/document.py
fairyscript/docx/oxml/exceptions.py
fairyscript/docx/oxml/ns.py
fairyscript/docx/oxml/numbering.py
