Metadata-Version: 1.2
Name: fairyscript
Version: 2.0.2
Summary: FairyScript is a language for compiling manuscripts.
Home-page: https://github.com/dekarrin/fairyscript
Author: Rebecca Nelson
Author-email: dekarrin.irl@gmail.com
License: UNKNOWN
Keywords: renpy visual novel screenplay script word office
Platform: UNKNOWN
Classifier: Programming Language :: Python :: 2.7
Classifier: Programming Language :: Python :: 3.3
Classifier: Programming Language :: Python :: 3.4
Classifier: Programming Language :: Python :: 3.5
Classifier: Programming Language :: Python :: 3.6
Classifier: Topic :: Software Development :: Compilers
Classifier: Development Status :: 5 - Production/Stable
Requires-Python: >=2.7,!=3.0.*,!=3.1.*,!=3.2.*
